LICENSE
README.md
setup.py
clash_for_python.egg-info/PKG-INFO
clash_for_python.egg-info/SOURCES.txt
clash_for_python.egg-info/dependency_links.txt
clash_for_python.egg-info/requires.txt
clash_for_python.egg-info/top_level.txt
clashpy/__init__.py
clashpy/clash.py